azure/mgmt/media/__init__.py
azure/mgmt/media/_azure_media_services.py
azure/mgmt/media/_configuration.py
azure/mgmt/media/_patch.py
azure/mgmt/media/_serialization.py
azure/mgmt/media/_vendor.py
azure/mgmt/media/_version.py
azure/mgmt/media/py.typed
azure/mgmt/media/aio/__init__.py
azure/mgmt/media/aio/_azure_media_services.py
azure/mgmt/media/aio/_configuration.py
azure/mgmt/media/aio/_patch.py
azure/mgmt/media/aio/operations/__init__.py
azure/mgmt/media/aio/operations/_account_filters_operations.py
azure/mgmt/media/aio/operations/_asset_filters_operations.py
azure/mgmt/media/aio/operations/_assets_operations.py
azure/mgmt/media/aio/operations/_content_key_policies_operations.py
azure/mgmt/media/aio/operations/_jobs_operations.py
azure/mgmt/media/aio/operations/_live_events_operations.py
azure/mgmt/media/aio/operations/_live_outputs_operations.py
azure/mgmt/media/aio/operations/_locations_operations.py
azure/mgmt/media/aio/operations/_media_services_operation_results_operations.py
azure/mgmt/media/aio/operations/_media_services_operation_statuses_operations.py
azure/mgmt/media/aio/operations/_mediaservices_operations.py
azure/mgmt/media/aio/operations/_operation_results_operations.py
azure/mgmt/media/aio/operations/_operation_statuses_operations.py
azure/mgmt/media/aio/operations/_operations.py
azure/mgmt/media/aio/operations/_patch.py
azure/mgmt/media/aio/operations/_private_endpoint_connections_operations.py
azure/mgmt/media/aio/operations/_private_link_resources_operations.py
azure/mgmt/media/aio/operations/_streaming_endpoints_operations.py
azure/mgmt/media/aio/operations/_streaming_locators_operations.py
azure/mgmt/media/aio/operations/_streaming_policies_operations.py
azure/mgmt/media/aio/operations/_tracks_operations.py
azure/mgmt/media/aio/operations/_transforms_operations.py
azure/mgmt/media/models/__init__.py
azure/mgmt/media/models/_azure_media_services_enums.py
azure/mgmt/media/models/_models_py3.py
azure/mgmt/media/models/_patch.py
azure_mgmt_media-10.2.1.dist-info/LICENSE
azure_mgmt_media-10.2.1.dist-info/METADATA
azure_mgmt_media-10.2.1.dist-info/WHEEL
azure_mgmt_media-10.2.1.dist-info/top_level.txt
azure_mgmt_media-10.2.1.dist-info/RECORD
